openprompt/__init__.py
openprompt/config.py
openprompt/default_config.py
openprompt/lm_bff_trainer.py
openprompt/pipeline_base.py
openprompt/prompt_base.py
openprompt/protoverb_trainer.py
openprompt/trainer.py
openprompt/data_utils/__init__.py
openprompt/data_utils/conditional_generation_dataset.py
openprompt/data_utils/data_processor.py
openprompt/data_utils/data_sampler.py
openprompt/data_utils/fewglue_dataset.py
openprompt/data_utils/huggingface_dataset.py
openprompt/data_utils/lama_dataset.py
openprompt/data_utils/nli_dataset.py
openprompt/data_utils/relation_classification_dataset.py
openprompt/data_utils/text_classification_dataset.py
openprompt/data_utils/typing_dataset.py
openprompt/data_utils/utils.py
openprompt/data_utils/ZH/__init__.py
openprompt/data_utils/ZH/closed_QA.py
openprompt/data_utils/ZH/coreference.py
openprompt/data_utils/ZH/entity_typing.py
openprompt/data_utils/ZH/generation.py
openprompt/data_utils/ZH/nli.py
openprompt/data_utils/ZH/paraphrase.py
openprompt/data_utils/ZH/processor.py
openprompt/data_utils/ZH/reading_comprehensation.py
openprompt/data_utils/ZH/relation.py
openprompt/data_utils/ZH/sentiment.py
openprompt/data_utils/ZH/summarization.py
openprompt/data_utils/ZH/topic_classification.py
openprompt/plms/__init__.py
openprompt/plms/lm.py
openprompt/plms/mlm.py
openprompt/plms/seq2seq.py
openprompt/plms/utils.py
openprompt/prompts/__init__.py
openprompt/prompts/automatic_verbalizer.py
openprompt/prompts/generation_verbalizer.py
openprompt/prompts/knowledgeable_verbalizer.py
openprompt/prompts/manual_template.py
openprompt/prompts/manual_verbalizer.py
openprompt/prompts/mixed_template.py
openprompt/prompts/one2one_verbalizer.py
openprompt/prompts/prefix_tuning_template.py
openprompt/prompts/prompt_generator.py
openprompt/prompts/prototypical_verbalizer.py
openprompt/prompts/ptr_prompts.py
openprompt/prompts/ptuning_prompts.py
openprompt/prompts/soft_template.py
openprompt/prompts/soft_verbalizer.py
openprompt/utils/__init__.py
openprompt-1.0.1.dist-info/LICENSE
openprompt-1.0.1.dist-info/METADATA
openprompt-1.0.1.dist-info/WHEEL
openprompt-1.0.1.dist-info/top_level.txt
openprompt-1.0.1.dist-info/RECORD
