Metadata-Version: 2.1
Name: openprompt
Version: 1.0.1
Summary: An open source framework for prompt-learning.
Home-page: https://github.com/thunlp/OpenPrompt
Author: Ning Ding, Shengding Hu, Weilin Zhao, Yulin Chen
Author-email: dingn18@mails.tsinghua.edu.cn
License: Apache
Keywords: PLM,prompt,AI,NLP
Classifier: Programming Language :: Python :: 3
Classifier: Programming Language :: Python :: 3.8
Classifier: Programming Language :: Python :: 3.9
Classifier: Intended Audience :: Developers
Classifier: Intended Audience :: Education
Classifier: Intended Audience :: Science/Research
Classifier: License :: OSI Approved :: Apache Software License
Classifier: Operating System :: OS Independent
Requires-Python: >=3.6.0
License-File: LICENSE
Requires-Dist: transformers (>=4.10.0)
Requires-Dist: sentencepiece (==0.1.96)
Requires-Dist: tqdm (>=4.62.2)
Requires-Dist: tensorboardX
Requires-Dist: nltk
Requires-Dist: yacs
Requires-Dist: dill
Requires-Dist: datasets
Requires-Dist: rouge (==1.0.0)
Requires-Dist: pyarrow
Requires-Dist: scipy
